dash_paperdragon/DashPaperdragon.py
dash_paperdragon/__init__.py
dash_paperdragon/_imports_.py
dash_paperdragon/dash_paperdragon.min.js
dash_paperdragon/dash_paperdragon.min.js.map
dash_paperdragon/metadata.json
dash_paperdragon/package-info.json
dash_paperdragon/utils.py
dash_paperdragon-0.1.91.dist-info/LICENSE
dash_paperdragon-0.1.91.dist-info/METADATA
dash_paperdragon-0.1.91.dist-info/WHEEL
dash_paperdragon-0.1.91.dist-info/top_level.txt
dash_paperdragon-0.1.91.dist-info/RECORD
