Metadata-Version: 2.1
Name: dash-paperdragon
Version: 0.1.91
Summary: OpenSeaDragon and PaperJS component for Dash and the DSA
Author: David Gutman <dagutman@gmail.com>
License: MIT
Classifier: Framework :: Dash
License-File: LICENSE
